japyconjugator/__init__.py
japyconjugator/adjectives/__init__.py
japyconjugator/adjectives/conjugation_helpers.py
japyconjugator/adjectives/conjugators.py
japyconjugator/adjectives/defs.py
japyconjugator/verbs/__init__.py
japyconjugator/verbs/conjugation_helpers.py
japyconjugator/verbs/conjugators.py
japyconjugator/verbs/defs.py
japyconjugator-1.1.0.dist-info/LICENSE
japyconjugator-1.1.0.dist-info/METADATA
japyconjugator-1.1.0.dist-info/WHEEL
japyconjugator-1.1.0.dist-info/top_level.txt
japyconjugator-1.1.0.dist-info/RECORD
