Metadata-Version: 2.1
Name: japyconjugator
Version: 1.1.0
Summary: A python package for conjugating verbs in the Japanese language.
Author: Simone Bondi
Project-URL: Repository, https://github.com/Shibodd/japyconjugator
Classifier: Development Status :: 4 - Beta
Classifier: License :: OSI Approved :: MIT License
Classifier: Operating System :: OS Independent
Classifier: Programming Language :: Python :: 3
Classifier: Topic :: Text Processing :: Linguistic
Requires-Python: >=3
License-File: LICENSE
